[
    {
        "word": "感親",
        "translation": "感冒了",
        "example_sentence": ""
    },
    {
        "word": "凍親",
        "translation": "著涼了",
        "example_sentence": ""
    },
    {
        "word": "跌親",
        "translation": "摔跤",
        "example_sentence": ""
    },
    {
        "word": "仆親",
        "translation": "仆倒",
        "example_sentence": ""
    },
    {
        "word": "撞親",
        "translation": "撞傷/碰到",
        "example_sentence": ""
    },
    {
        "word": "扭親",
        "translation": "扭傷",
        "example_sentence": ""
    },
    {
        "word": "屈親",
        "translation": "扭到",
        "example_sentence": ""
    },
    {
        "word": "𠝹親",
        "translation": "割傷",
        "example_sentence": ""
    },
    {
        "word": "整親",
        "translation": "弄傷/弄到",
        "example_sentence": ""
    },
    {
        "word": "辣親",
        "translation": "燙到",
        "example_sentence": ""
    }
]